{
  "development": {
    "username": "lms_user1",
    "password": "763%*&%gshsks&^#$^#",
    "database": "lms_db",
    "host": "localhost",
    "dialect": "postgres",
    "mail": {
        "host": "sandbox.smtp.mailtrap.io",
        "username": "9f798c435b0365",
        "password": "7e8d5fea21ae3d",
        "port": 587
    }
  },
  "test": {
    "username": "lms_staging",
    "password": "e#1^2O%r:2{B$20s&<!",
    "database": "lms_staging",
    "host": "127.0.0.1",
    "dialect": "postgres",
    "mail": {
        "host": "",
        "username": "",
        "password": ""
    }
  },
  "production": {
    "username": "lms_staging",
    "password": "e#1^2O%r:2{B$20s&<!",
    "database": "lms_staging",
    "host": "localhost",
    "dialect": "postgres",
    "mail": {
        "host": "smtppro.zoho.in",
        "username": "publisher@khabriya.in",
        "password": "Sandeep#141414",
        "port": 587
    }
  },
  "secret": "AJT_Lbim_0f6bd8a808ea3e9996b3aee1900aa2e8",
  "jwt_secret": "topTV_sq2d1yYfSetXXnmOb7HzKQNk0WwvdK36",
  "accountSid": "",
  "authToken": "",
  "authorApiURL": "https://news.khabriya.in/wp-json/wp/v2/users/"
}
